SpaDOT/__init__.py
SpaDOT/__main__.py
SpaDOT/analyze.py
SpaDOT/cli.py
SpaDOT/config.yaml
SpaDOT/preprocess.py
SpaDOT/train.py
SpaDOT/model/SpaDOT.py
SpaDOT/model/__init__.py
SpaDOT/model/decoder.py
SpaDOT/model/encoder.py
SpaDOT/model/svgp.py
SpaDOT/utils/__init__.py
SpaDOT/utils/_analyze_utils.py
SpaDOT/utils/_preprocess_utils.py
SpaDOT/utils/_train_utils.py
SpaDOT/utils/_utils.py
SpaDOT/utils/OT_loss/__init__.py
SpaDOT/utils/OT_loss/libot.so
SpaDOT/utils/OT_loss/ot_func.py
SpaDOT/utils/OT_loss/ot_solvers.py
SpaDOT/utils/sctransform/__init__.py
SpaDOT/utils/sctransform/bw.py
SpaDOT/utils/sctransform/ksmooth.py
SpaDOT/utils/sctransform/scale_data.py
SpaDOT/utils/sctransform/sctransform.py
SpaDOT/utils/sctransform/sctransform_utils.py
SpaDOT/utils/sctransform/vst.py
spadot-1.0.3.dist-info/licenses/LICENSE
spadot-1.0.3.dist-info/METADATA
spadot-1.0.3.dist-info/WHEEL
spadot-1.0.3.dist-info/entry_points.txt
spadot-1.0.3.dist-info/top_level.txt
spadot-1.0.3.dist-info/RECORD
