Metadata-Version: 2.4
Name: SpaDOT
Version: 1.0.3
Summary: Package for paper: Optimal transport modeling uncovers spatial domain dynamics in spatiotemporal transcriptomics
Author-email: Wenjing Ma <mawenjing1993@gmail.com>
License: MIT
Project-URL: homepage, https://marvinquiet.github.io/SpaDOT
Classifier: Programming Language :: Python :: 3
Classifier: License :: OSI Approved :: MIT License
Classifier: Operating System :: OS Independent
Requires-Python: >=3.9
License-File: LICENSE
Requires-Dist: torch==2.5.0
Requires-Dist: torchvision
Requires-Dist: torchaudio
Requires-Dist: anndata==0.9.1
Requires-Dist: scanpy==1.9.8
Requires-Dist: numpy<2.0.0
Requires-Dist: chi2comb==0.1.0
Requires-Dist: KDEpy==1.1.12
Requires-Dist: wot
Requires-Dist: pandas
Requires-Dist: scipy
Requires-Dist: scikit-learn
Requires-Dist: matplotlib
Requires-Dist: seaborn
Requires-Dist: tqdm
Requires-Dist: pyyaml
Requires-Dist: louvain
Provides-Extra: dev
Requires-Dist: pytest; extra == "dev"
Requires-Dist: black; extra == "dev"
Requires-Dist: ruff; extra == "dev"
Dynamic: license-file
